{
  "type": "groupeDeBoutons",
  "taille": "petite",
  "boutons": [
    {
      "type": "bouton",
      "id": "calendar",
      "icone": "Calendar",
      "texte": null,
      "url": null,
      "command": "cmd-FaisonsConnaissance",
      "tooltip": "faisons connaissance",
      "e2eID": "b9"
    },
    {
      "type": "bouton",
      "id": "email",
      "icone": "Mail",
      "texte": null,
      "url": "mailto:alain@maep.fr",
      "command": "cmd-email",
      "e2eID": "b10"
    },
    {
      "type": "bouton",
      "id": "youtube",
      "icone": "Youtube",
      "texte": null,
      "url": "https://www.youtube.com/@m-alain-et-possible",
      "command": "cmd-YouTube",
      "e2eID": "b11"
    },
    {
      "type": "bouton",
      "id": "linkedin",
      "icone": "Linkedin",
      "texte": null,
      "url": "https://www.linkedin.com/in/alain-meunier-maep/",
      "command": "cmd-Linkedin",
      "e2eID": "b12"
    },
    {
      "type": "bouton",
      "id": "sitemap",
      "icone": "Plan du site",
      "texte": null,
      "url": null,
      "command": "cmd-PlanDuSite",
      "e2eID": "b13"
    },
    {
      "type": "bouton",
      "id": "about-site",
      "icone": "Info",
      "texte": null,
      "url": null,
      "command": "cmd-AProposDuSite",
      "e2eID": "b15"
    }
  ]
}